lsms/__init__.py
lsms/dta_concordance.py
lsms/from_dta.py
lsms/tools.py
lsms-0.4.7.dist-info/LICENSE.txt
lsms-0.4.7.dist-info/METADATA
lsms-0.4.7.dist-info/WHEEL
lsms-0.4.7.dist-info/top_level.txt
lsms-0.4.7.dist-info/RECORD
