Metadata-Version: 2.1
Name: lsms
Version: 0.4.7
Summary: Tools for working with Living Standards Measurement Surveys
Home-page: https://bitbucket.org/eligon/LSMS
Author: Ethan Ligon
Author-email: ligon@berkeley.edu
License: Creative Commons Attribution-Noncommercial-ShareAlike 4.0 International license
License-File: LICENSE.txt
